flyteadmin/__init__.py
flyteadmin/api_client.py
flyteadmin/configuration.py
flyteadmin/rest.py
flyteadmin/api/__init__.py
flyteadmin/api/admin_service_api.py
flyteadmin/models/__init__.py
flyteadmin/models/admin_abort_metadata.py
flyteadmin/models/admin_affinity.py
flyteadmin/models/admin_annotations.py
flyteadmin/models/admin_auth.py
flyteadmin/models/admin_auth_role.py
flyteadmin/models/admin_cluster_assignment.py
flyteadmin/models/admin_cluster_resource_attributes.py
flyteadmin/models/admin_cron_schedule.py
flyteadmin/models/admin_domain.py
flyteadmin/models/admin_email_notification.py
flyteadmin/models/admin_execution.py
flyteadmin/models/admin_execution_closure.py
flyteadmin/models/admin_execution_cluster_label.py
flyteadmin/models/admin_execution_create_request.py
flyteadmin/models/admin_execution_create_response.py
flyteadmin/models/admin_execution_list.py
flyteadmin/models/admin_execution_metadata.py
flyteadmin/models/admin_execution_queue_attributes.py
flyteadmin/models/admin_execution_recover_request.py
flyteadmin/models/admin_execution_relaunch_request.py
flyteadmin/models/admin_execution_spec.py
flyteadmin/models/admin_execution_state.py
flyteadmin/models/admin_execution_state_change_details.py
flyteadmin/models/admin_execution_terminate_request.py
flyteadmin/models/admin_execution_terminate_response.py
flyteadmin/models/admin_execution_update_request.py
flyteadmin/models/admin_execution_update_response.py
flyteadmin/models/admin_fixed_rate.py
flyteadmin/models/admin_fixed_rate_unit.py
flyteadmin/models/admin_get_version_response.py
flyteadmin/models/admin_labels.py
flyteadmin/models/admin_launch_plan.py
flyteadmin/models/admin_launch_plan_closure.py
flyteadmin/models/admin_launch_plan_create_request.py
flyteadmin/models/admin_launch_plan_create_response.py
flyteadmin/models/admin_launch_plan_list.py
flyteadmin/models/admin_launch_plan_metadata.py
flyteadmin/models/admin_launch_plan_spec.py
flyteadmin/models/admin_launch_plan_state.py
lyteadminstub-1.0.0.dist-info/METADATA
lyteadminstub-1.0.0.dist-info/WHEEL
lyteadminstub-1.0.0.dist-info/top_level.txt
lyteadminstub-1.0.0.dist-info/RECORD
