Metadata-Version: 2.1
Name: lyteadminstub
Version: 1.0.0
Summary: lyteidl/service/admin.proto
Home-page: 
Author-email: 
Keywords: Swagger,flyteidl/service/admin.proto
Requires-Dist: certifi (>=2017.4.17)
Requires-Dist: python-dateutil (>=2.1)
Requires-Dist: six (>=1.10)
Requires-Dist: urllib3 (>=1.23)
